setup.py
paulo_distributions/Binomialdistribution.py
paulo_distributions/Gaussiandistribution.py
paulo_distributions/Generaldistribution.py
paulo_distributions/__init__.py
paulo_distributions.egg-info/PKG-INFO
paulo_distributions.egg-info/SOURCES.txt
paulo_distributions.egg-info/dependency_links.txt
paulo_distributions.egg-info/not-zip-safe
paulo_distributions.egg-info/top_level.txt