Metadata-Version: 1.0
Name: paulo-distributions
Version: 0.1
Summary: Gaussian and Binomial distributions
Home-page: UNKNOWN
Author: Paulo Arantes
Author-email: UNKNOWN
License: UNKNOWN
Platform: UNKNOWN
